MANIFEST.in
README.md
setup.py
django_viewgroups.egg-info/PKG-INFO
django_viewgroups.egg-info/SOURCES.txt
django_viewgroups.egg-info/dependency_links.txt
django_viewgroups.egg-info/not-zip-safe
django_viewgroups.egg-info/requires.txt
django_viewgroups.egg-info/top_level.txt
viewsets/__init__.py
viewsets/base.py
viewsets/fields.py
viewsets/inline.py
viewsets/models.py
viewsets/views.py
viewsets/widgets.py
viewsets/management/__init__.py
viewsets/management/commands/__init__.py
viewsets/mixins/__init__.py
viewsets/mixins/actions.py
viewsets/mixins/base.py
viewsets/mixins/filter.py
viewsets/mixins/manager.py
viewsets/mixins/search.py
viewsets/mixins/sort.py
viewsets/templates/base/base.html
viewsets/templates/base/create.html
viewsets/templates/base/delete.html
viewsets/templates/base/detail.html
viewsets/templates/base/list.html
viewsets/templates/base/pagination.html
viewsets/templates/base/update.html
viewsets/templates/base/actions/delete_selected.html
viewsets/templates/forms/bootstrap.html
viewsets/templates/forms/inline.html
viewsets/templates/forms/stacked_inline.html
viewsets/templates/forms/tabular_inline.html
viewsets/templatetags/__init__.py
viewsets/templatetags/form_tags.py
viewsets/templatetags/paginator.py
viewsets/templatetags/viewgroups_tags.py